pcapkit/__init__.py
pcapkit/__main__.py
pcapkit/all.py
pcapkit/py.typed
pcapkit/const/__init__.py
pcapkit/const/arp/__init__.py
pcapkit/const/arp/hardware.py
pcapkit/const/arp/operation.py
pcapkit/const/ftp/__init__.py
pcapkit/const/ftp/command.py
pcapkit/const/ftp/return_code.py
pcapkit/const/hip/__init__.py
pcapkit/const/hip/certificate.py
pcapkit/const/hip/cipher.py
pcapkit/const/hip/di.py
pcapkit/const/hip/ecdsa_curve.py
pcapkit/const/hip/ecdsa_low_curve.py
pcapkit/const/hip/eddsa_curve.py
pcapkit/const/hip/esp_transform_suite.py
pcapkit/const/hip/group.py
pcapkit/const/hip/hi_algorithm.py
pcapkit/const/hip/hit_suite.py
pcapkit/const/hip/nat_traversal.py
pcapkit/const/hip/notify_message.py
pcapkit/const/hip/packet.py
pcapkit/const/hip/parameter.py
pcapkit/const/hip/registration.py
pcapkit/const/hip/registration_failure.py
pcapkit/const/hip/suite.py
pcapkit/const/hip/transport.py
pcapkit/const/http/__init__.py
pcapkit/const/http/error_code.py
pcapkit/const/http/frame.py
pcapkit/const/http/method.py
pcapkit/const/http/setting.py
pcapkit/const/http/status_code.py
pcapkit/const/ipv4/__init__.py
pcapkit/const/ipv4/classification_level.py
pcapkit/const/ipv4/option_class.py
pcapkit/const/ipv4/option_number.py
pcapkit/const/ipv4/protection_authority.py
pcapkit/const/ipv4/qs_function.py
pcapkit/const/ipv4/router_alert.py
pcapkit/const/ipv4/tos_del.py
pcapkit/const/ipv4/tos_ecn.py
pcapkit/const/ipv4/tos_pre.py
pcapkit/const/ipv4/tos_rel.py
pcapkit/const/ipv4/tos_thr.py
pcapkit/const/ipv4/ts_flag.py
pcapkit/const/ipv6/__init__.py
pcapkit/const/ipv6/extension_header.py
pcapkit/const/ipv6/option.py
pcapkit/const/ipv6/option_action.py
pcapkit/const/ipv6/qs_function.py
pcapkit/const/ipv6/router_alert.py
pcapkit/const/ipv6/routing.py
pcapkit/const/ipv6/seed_id.py
pcapkit/const/ipv6/smf_dpd_mode.py
pcapkit/const/ipv6/tagger_id.py
pcapkit/const/ipx/__init__.py
pcapkit/const/ipx/packet.py
pcapkit/const/ipx/socket.py
pcapkit/const/l2tp/__init__.py
pcapkit/const/l2tp/type.py
pypcapkit-1.3.5.post34.dist-info/LICENSE
pypcapkit-1.3.5.post34.dist-info/METADATA
pypcapkit-1.3.5.post34.dist-info/WHEEL
pypcapkit-1.3.5.post34.dist-info/entry_points.txt
pypcapkit-1.3.5.post34.dist-info/top_level.txt
pypcapkit-1.3.5.post34.dist-info/RECORD
