Metadata-Version: 2.1
Name: pypcapkit
Version: 1.3.5.post34
Summary: PyPCAPKit: comprehensive network packet analysis library
Author-email: Jarry Shaw <jarryshaw@icloud.com>
Maintainer: Jarry Shaw
License: BSD 3-Clause License
Project-URL: homepage, https://jarryshaw.github.io/PyPCAPKit/
Project-URL: documentation, https://jarryshaw.github.io/PyPCAPKit/
Project-URL: repository, https://github.com/JarryShaw/PyPCAPKit
Project-URL: changelog, https://github.com/JarryShaw/PyPCAPKit/releases
Keywords: network,pcap,packet
Classifier: Development Status :: 5 - Production/Stable
Classifier: Environment :: Console
Classifier: Environment :: MacOS X
Classifier: Environment :: Win32 (MS Windows)
Classifier: Intended Audience :: Developers
Classifier: Intended Audience :: Information Technology
Classifier: Intended Audience :: Science/Research
Classifier: Intended Audience :: System Administrators
Classifier: Intended Audience :: Telecommunications Industry
Classifier: License :: OSI Approved :: BSD License
Classifier: Operating System :: OS Independent
Classifier: Programming Language :: Python :: 3
Classifier: Programming Language :: Python :: 3.6
Classifier: Programming Language :: Python :: 3.7
Classifier: Programming Language :: Python :: 3.8
Classifier: Programming Language :: Python :: 3.9
Classifier: Programming Language :: Python :: 3.10
Classifier: Programming Language :: Python :: 3.11
Classifier: Programming Language :: Python :: 3 :: Only
Classifier: Programming Language :: Python :: Implementation :: CPython
Classifier: Programming Language :: Python :: Implementation :: PyPy
Classifier: Topic :: Security
Classifier: Topic :: System :: Networking
Classifier: Topic :: System :: Networking :: Monitoring
Classifier: Topic :: Utilities
Classifier: Typing :: Typed
Requires-Python: <4,>=3.6
License-File: LICENSE
Requires-Dist: dictdumper ~=0.8.0
Requires-Dist: chardet
Requires-Dist: aenum
Requires-Dist: tbtrim >=0.2.1
Requires-Dist: typing-extensions ; python_version < "3.11"
Requires-Dist: bpc-f2format ; python_version < "3.6"
Requires-Dist: bpc-poseur ; python_version < "3.8"
Requires-Dist: bpc-walrus ; python_version < "3.8"
Requires-Dist: pathlib2 >=2.3.2 ; python_version == "3.4"
Provides-Extra: dpkt
Requires-Dist: dpkt ; extra == 'dpkt'
Provides-Extra: pyshark
Requires-Dist: pyshark ; extra == 'pyshark'
Provides-Extra: scapy
Requires-Dist: scapy ; extra == 'scapy'
Provides-Extra: all
Requires-Dist: emoji ; extra == 'all'
Requires-Dist: dpkt ; extra == 'all'
Requires-Dist: scapy ; extra == 'all'
Requires-Dist: pyshark ; extra == 'all'
Requires-Dist: requests[socks] ; extra == 'all'
Requires-Dist: beautifulsoup4[html5lib] ; extra == 'all'
Provides-Extra: cli
Requires-Dist: emoji ; extra == 'cli'
Provides-Extra: docs
Requires-Dist: Sphinx >=6.1.3 ; extra == 'docs'
Requires-Dist: furo ; extra == 'docs'
Requires-Dist: sphinx-autodoc-typehints ; extra == 'docs'
Requires-Dist: sphinx-opengraph ; extra == 'docs'
Requires-Dist: sphinx-copybutton ; extra == 'docs'
Requires-Dist: typing-extensions ; extra == 'docs'
Requires-Dist: mypy-extensions ; extra == 'docs'
Provides-Extra: vendor
Requires-Dist: requests[socks] ; extra == 'vendor'
Requires-Dist: beautifulsoup4[html5lib] ; extra == 'vendor'
